mcp_bigquery_biomedical/__init__.py
mcp_bigquery_biomedical/database.py
mcp_bigquery_biomedical/handlers.py
mcp_bigquery_biomedical/memo_manager.py
mcp_bigquery_biomedical/prompt_config.py
mcp_bigquery_biomedical/prompts.py
mcp_bigquery_biomedical/resources.py
mcp_bigquery_biomedical/server.py
mcp_bigquery_biomedical/tools.py
mcp_bigquery_biomedical/resources/database_schema.json
mcp_bigquery_biomedical-0.1.3.dist-info/METADATA
mcp_bigquery_biomedical-0.1.3.dist-info/WHEEL
mcp_bigquery_biomedical-0.1.3.dist-info/entry_points.txt
mcp_bigquery_biomedical-0.1.3.dist-info/licenses/LICENSE
mcp_bigquery_biomedical-0.1.3.dist-info/RECORD
